python_proptest/__init__.py
python_proptest/core/__init__.py
python_proptest/core/decorators.py
python_proptest/core/either.py
python_proptest/core/generator.py
python_proptest/core/option.py
python_proptest/core/property.py
python_proptest/core/shrinker.py
python_proptest/core/shrinker_utils.py
python_proptest/core/stateful.py
python_proptest/core/stream.py
python_proptest/core/try_.py
python_proptest/core/combinator/__init__.py
python_proptest/core/combinator/construct.py
python_proptest/core/combinator/element_of.py
python_proptest/core/combinator/just.py
python_proptest/core/combinator/lazy.py
python_proptest/core/combinator/one_of.py
python_proptest/core/generator/__init__.py
python_proptest/core/generator/aggregate.py
python_proptest/core/generator/base.py
python_proptest/core/generator/bool.py
python_proptest/core/generator/chain.py
python_proptest/core/generator/dict.py
python_proptest/core/generator/floating.py
python_proptest/core/generator/gen.py
python_proptest/core/generator/integral.py
python_proptest/core/generator/list.py
python_proptest/core/generator/set.py
python_proptest/core/generator/string.py
python_proptest/core/generator/transform.py
python_proptest/core/shrinker/__init__.py
python_proptest/core/shrinker/bool.py
python_proptest/core/shrinker/floating.py
python_proptest/core/shrinker/integral.py
python_proptest/core/shrinker/list.py
python_proptest/core/shrinker/pair.py
python_proptest/core/shrinker/string.py
python_proptest/core/shrinker/tuple.py
python_proptest-0.1.5.dist-info/licenses/LICENSE
python_proptest-0.1.5.dist-info/METADATA
python_proptest-0.1.5.dist-info/WHEEL
python_proptest-0.1.5.dist-info/top_level.txt
python_proptest-0.1.5.dist-info/RECORD
