Metadata-Version: 2.4
Name: python-proptest
Version: 0.1.5
Summary: python-proptest: A comprehensive Python property-based testing library with pytest and unittest integration
Author-email: kindone <jradoo@gmail.com>
Maintainer-email: kindone <jradoo@gmail.com>
License: MIT License
Project-URL: Homepage, https://github.com/kindone/python-proptest
Project-URL: Repository, https://github.com/kindone/python-proptest
Project-URL: Documentation, https://kindone.github.io/python-proptest
Project-URL: Bug Tracker, https://github.com/kindone/python-proptest/issues
Project-URL: Source Code, https://github.com/kindone/python-proptest
Keywords: testing,property-based-testing,pytest,unittest,hypothesis,quickcheck,generative-testing,test-data-generation,shrinking,minimal-counterexamples
Classifier: Development Status :: 4 - Beta
Classifier: Intended Audience :: Developers
Classifier: Operating System :: OS Independent
Classifier: Programming Language :: Python :: 3
Classifier: Programming Language :: Python :: 3.8
Classifier: Programming Language :: Python :: 3.9
Classifier: Programming Language :: Python :: 3.10
Classifier: Programming Language :: Python :: 3.11
Classifier: Programming Language :: Python :: 3.12
Classifier: Topic :: Software Development :: Testing
Classifier: Topic :: Software Development :: Quality Assurance
Classifier: Topic :: Software Development :: Libraries :: Python Modules
Classifier: Framework :: Pytest
Requires-Python: >=3.8
License-File: LICENSE
Provides-Extra: dev
Requires-Dist: pytest<8.4.0,>=7.0.0; extra == "dev"
Requires-Dist: pytest-cov>=4.0.0; extra == "dev"
Requires-Dist: mypy>=1.0.0; extra == "dev"
Requires-Dist: black>=22.0.0; extra == "dev"
Requires-Dist: isort>=5.0.0; extra == "dev"
Requires-Dist: flake8>=5.0.0; extra == "dev"
Requires-Dist: bandit>=1.7.0; extra == "dev"
Requires-Dist: safety>=2.0.0; extra == "dev"
Provides-Extra: docs
Requires-Dist: mkdocs>=1.4.0; extra == "docs"
Requires-Dist: mkdocs-material>=9.0.0; extra == "docs"
Requires-Dist: mkdocs-mermaid2-plugin>=0.6.0; extra == "docs"
Requires-Dist: mkdocs-git-revision-date-localized-plugin>=1.2.0; extra == "docs"
Requires-Dist: pymdown-extensions>=9.0.0; extra == "docs"
Dynamic: license-file
